gimulator/__init__.py
gimulator/client.py
gimulator/proto_pb2.py
gimulator/proto_pb2_grpc.py
gimulator_py-0.1.10.dist-info/LICENSE
gimulator_py-0.1.10.dist-info/METADATA
gimulator_py-0.1.10.dist-info/WHEEL
gimulator_py-0.1.10.dist-info/top_level.txt
gimulator_py-0.1.10.dist-info/RECORD
