Metadata-Version: 2.1
Name: gimulator-py
Version: 0.1.10
Summary: Gimulator client for Python
Home-page: https://github.com/Gimulator/client-python
Author: RoboEpics Authors
Author-email: info@roboepics.com
License: MIT
Classifier: License :: OSI Approved :: MIT License
Classifier: Programming Language :: Python
Classifier: Programming Language :: Python :: 3
Classifier: Programming Language :: Python :: 3.6
Requires-Python: >=3.6.0
License-File: LICENSE
Requires-Dist: grpcio
Requires-Dist: grpcio-tools
Requires-Dist: protobuf
